pretalx_plugin_build/__init__.py
pretalx_plugin_build/build.py
pretalx_plugin_build-1.0.0.dist-info/METADATA
pretalx_plugin_build-1.0.0.dist-info/WHEEL
pretalx_plugin_build-1.0.0.dist-info/top_level.txt
pretalx_plugin_build-1.0.0.dist-info/RECORD
